ingot_protobuf/__init__.py
ingot_protobuf/bootstrap/__init__.py
ingot_protobuf/bootstrap/scaffolding/__init__.py
ingot_protobuf/scripts/__init__.py
ingot_protobuf/scripts/ingot_protobuf.py
ingot_protobuf/tests/__init__.py
ingot_protobuf/tests/functionals/__init__.py
ingot_protobuf/tests/units/__init__.py
ingot_protobuf/tests/units/scripts/__init__.py
ingot_protobuf/tests/units/scripts/test_ingot_protobuf.py
scripts/__init__.py
scripts/create_package_version_file.py
ingot_protobuf-0.1.0.dist-info/LICENSE
ingot_protobuf-0.1.0.dist-info/METADATA
ingot_protobuf-0.1.0.dist-info/WHEEL
ingot_protobuf-0.1.0.dist-info/entry_points.txt
ingot_protobuf-0.1.0.dist-info/top_level.txt
ingot_protobuf-0.1.0.dist-info/RECORD
